PyThief/PyThief.py
PyThief/__init__.py
PyThief/aggregation.py
PyThief/fit_helper.py
PyThief/utils.py
PyThief/models/__init__.py
PyThief/models/arima.py
PyThief/models/base_model.py
PyThief/models/croston.py
PyThief/models/ets.py
PyThief/models/mean.py
PyThief/models/median.py
PyThief/models/naive.py
PyThief/models/snaive.py
PyThief/models/theta.py
PyThief/models/thymeboost.py
PyThief/recon_methods/__init__.py
PyThief/recon_methods/mse.py
PyThief/recon_methods/ols.py
PyThief/recon_methods/wls.py
Tests/__init__.py
Tests/aggTest.py
Tests/integrationTest.py
Tests/reconTests.py
Tests/unitTests.py
Tests/utilsTest.py
PyThief-0.1.1.dist-info/METADATA
PyThief-0.1.1.dist-info/WHEEL
PyThief-0.1.1.dist-info/top_level.txt
PyThief-0.1.1.dist-info/RECORD
