Metadata-Version: 2.1
Name: PyThief
Version: 0.1.1
Summary: Python verison of Thief forecasting.
Author: Charles Howard
Keywords: forecasting,time series,time aggregation,hierarchical
Classifier: Programming Language :: Python :: 3
Classifier: License :: OSI Approved :: MIT License
Classifier: Operating System :: OS Independent
Requires-Dist: numpy
Requires-Dist: pandas
Requires-Dist: darts
Requires-Dist: scikit-learn
Requires-Dist: scipy
Requires-Dist: more-itertools
Requires-Dist: matplotlib
Requires-Dist: tqdm
Requires-Dist: pmdarima
